[{"anatomy": "unknown", "Metabolomics": 78425, "HMP": 55221, "KidsFirst": 17512, "LINCS": 5519, "4DN": 3433}, {"anatomy": "breast", "LINCS": 71493}, {"anatomy": "large intestine", "LINCS": 70082, "4DN": 630}, {"anatomy": "prostate gland", "LINCS": 40582, "4DN": 4}, {"anatomy": "kidney", "LINCS": 38984, "4DN": 94}, {"anatomy": "skin of body", "LINCS": 38374}, {"anatomy": "pancreas", "LINCS": 32483, "4DN": 4}, {"anatomy": "blood", "KidsFirst": 19691, "LINCS": 1220, "HMP": 636}, {"anatomy": "lung", "LINCS": 17450}, {"anatomy": "central nervous system", "LINCS": 10022, "4DN": 4}, {"anatomy": "feces", "HMP": 7627}, {"anatomy": "skin of cheek", "KidsFirst": 7474}, {"anatomy": "other", "KidsFirst": 11346, "LINCS": 31477, "HMP": 28572, "4DN": 3690}]